easyspec/__init__.py
easyspec/analysis/__init__.py
easyspec/analysis/analysis.py
easyspec/analysis/aux_fit_lines.py
easyspec/analysis/line_models.py
easyspec/analysis/lines/astro_lines.dat
easyspec/cleaning/__init__.py
easyspec/cleaning/cleaning.py
easyspec/extraction/__init__.py
easyspec/extraction/extraction.py
easyspec/extraction/airmass/apo_airmass_extinction.txt
easyspec/extraction/airmass/ctio_airmass_extinction.txt
easyspec/extraction/airmass/kpno_airmass_extinction.txt
easyspec/extraction/airmass/lapalma_airmass_extinction.txt
easyspec/extraction/airmass/mko_airmass_extinction.txt
easyspec/extraction/airmass/mtham_airmass_extinction.txt
easyspec/extraction/airmass/paranal_airmass_extinction.txt
easyspec/extraction/standards/blackbody/b.dat
easyspec/extraction/standards/blackbody/h.dat
easyspec/extraction/standards/blackbody/i.dat
easyspec/extraction/standards/blackbody/j.dat
easyspec/extraction/standards/blackbody/k.dat
easyspec/extraction/standards/blackbody/l.dat
easyspec/extraction/standards/blackbody/lprime.dat
easyspec/extraction/standards/blackbody/m.dat
easyspec/extraction/standards/blackbody/mkbbcal.cl
easyspec/extraction/standards/blackbody/mkbbdat.cl
easyspec/extraction/standards/blackbody/params.dat
easyspec/extraction/standards/blackbody/r.dat
easyspec/extraction/standards/blackbody/standards.men
easyspec/extraction/standards/blackbody/u.dat
easyspec/extraction/standards/blackbody/v.dat
easyspec/extraction/standards/bstdscal/hr3454.dat
easyspec/extraction/standards/bstdscal/hr3982.dat
easyspec/extraction/standards/bstdscal/hr4468.dat
easyspec/extraction/standards/bstdscal/hr4534.dat
easyspec/extraction/standards/bstdscal/hr5191.dat
easyspec/extraction/standards/bstdscal/hr5511.dat
easyspec/extraction/standards/bstdscal/hr7001.dat
easyspec/extraction/standards/bstdscal/hr718.dat
easyspec/extraction/standards/bstdscal/hr7596.dat
easyspec/extraction/standards/bstdscal/hr7950.dat
easyspec/extraction/standards/bstdscal/hr8634.dat
easyspec-1.0.3.4.dist-info/LICENSE
easyspec-1.0.3.4.dist-info/METADATA
easyspec-1.0.3.4.dist-info/WHEEL
easyspec-1.0.3.4.dist-info/top_level.txt
easyspec-1.0.3.4.dist-info/RECORD
