Metadata-Version: 2.1
Name: easyspec
Version: 1.0.3.4
Summary: The easiest way to do long-slit spectroscopy
Author: Raniere de Menezes
Author-email: <easyfermi@gmail.com>
Keywords: python,optical spectra,long-slit,spectroscopy,infrared,infrared spectroscopy,ultraviolet
Classifier: Development Status :: 5 - Production/Stable
Classifier: Intended Audience :: Science/Research
Classifier: Programming Language :: Python :: 3
Classifier: Operating System :: Unix
Classifier: Operating System :: MacOS :: MacOS X
License-File: LICENSE
